{
  "posts":[
     {
        "id":1,
        "title":"json-server",
        "author":"typicode"
     }
  ],
  "products":[
     {
        "id":"34727803",
        "name":"Galaxy A51 128 GB Beyaz Cep Telefonu (Samsung Türkiye Garantili)",
        "sku":"SKU-N100",
        "brand":{
           "id":3228,
           "name":"Samsung"
        },
        "slug":"#",
        "images":[
           "https://cdn.dsmcdn.com/assets/product/media/images/20200114/17/2203208/62065642/1/1_org.jpg"
        ],
        "price":{
           "sellingPrice":2543,
           "originalPrice":2899
        }
     },
     {
        "id":"34727804",
        "name":"Galaxy M20 32 GB Koyu Mavi Cep Telefonu (Samsung Türkiye Garantili)",
        "sku":"SKU-N101",
        "brand":{
           "id":3228,
           "name":"Samsung"
        },
        "slug":"#",
        "images":[
           "https://cdn.dsmcdn.com/assets/product/images/1620/17955281/1/1_org.jpg"
        ],
        "price":{
           "sellingPrice":1229,
           "originalPrice":1699
        }
     },
     {
        "id":"34727805",
        "name":"iPhone 11 64GB Beyaz (Apple Türkiye Garantili)",
        "sku":"SKU-N102",
        "brand":{
           "id":1617,
           "name":"Apple"
        },
        "slug":"#",
        "images":[
           "https://cdn.dsmcdn.com/assets/product/media/images/20191017/19/437470/57616612/1/1_org.jpg"
        ],
        "price":{
           "sellingPrice":6759,
           "originalPrice":7999
        }
     },
     {
        "id":"34727806",
        "name":"iPhone XR 64GB Beyaz - Apple Türkiye Garantili",
        "sku":"SKU-N102",
        "brand":{
           "id":1617,
           "name":"Apple"
        },
        "slug":"#",
        "images":[
           "https://cdn.dsmcdn.com/Assets/ProductImages/oa/54/4112636/22/190198770912_3_org.jpg"
        ],
        "price":{
           "sellingPrice":4149,
           "originalPrice":4149
        }
     },
     {
      "id":"34727807",
      "name":"iPhone 11 64GB Siyah (Apple Türkiye Garantili)",
      "sku":"SKU-N100",
      "brand":{
         "id":3228,
         "name":"Apple"
      },
      "slug":"#",
      "images":[
         "https://cdn.dsmcdn.com/assets/product/media/images/20191017/19/437470/57616611/1/1_org.jpg"
      ],
      "price":{
         "sellingPrice":6759,
         "originalPrice":7999
      }
   },
   {
      "id":"34727808",
      "name":"iPhone 7 32GB Mat Siyah ( Apple Türkiye Garantili )",
      "sku":"SKU-N121",
      "brand":{
         "id":3228,
         "name":"Apple"
      },
      "slug":"#",
      "images":[
         "https://cdn.dsmcdn.com/Assets/ProductImages/oa/54/1064029/31/190198067043_3_org.jpg"
      ],
      "price":{
         "sellingPrice":2990,
         "originalPrice":0
      }
   },
   {
      "id":"34727809",
      "name":"Redmi Note 8 128 GB Siyah ( Xiaomi Türkiye Garantili )",
      "sku":"SKU-N102",
      "brand":{
         "id":1617,
         "name":"Xiaomi"
      },
      "slug":"#",
      "images":[
         "https://cdn.dsmcdn.com/assets/product/media/images/20191017/17/437463/57617125/1/1_org.jpg"
      ],
      "price":{
         "sellingPrice":1809,
         "originalPrice":2149
      }
   },
   {
      "id":"34727816",
      "name":"iPhone XR 64GB Beyaz - Apple Türkiye Garantili",
      "sku":"SKU-N102",
      "brand":{
         "id":1617,
         "name":"Apple"
      },
      "slug":"#",
      "images":[
         "https://cdn.dsmcdn.com/Assets/ProductImages/oa/54/4112636/22/190198770912_3_org.jpg"
      ],
      "price":{
         "sellingPrice":4149,
         "originalPrice":4149
      }
   }
  ],
  "comments":[
     {
        "id":1,
        "body":"some comment",
        "postId":1
     }
  ],
  "profile":{
     "name":"typicode"
  }
}